sliver/__init__.py
sliver/_protocols.py
sliver/beacon.py
sliver/client.py
sliver/config.py
sliver/interactive.py
sliver/protobuf.py
sliver/session.py
sliver/utils.py
sliver/pb/__init__.py
sliver/pb/clientpb/__init__.py
sliver/pb/clientpb/client_pb2.py
sliver/pb/clientpb/client_pb2.pyi
sliver/pb/commonpb/__init__.py
sliver/pb/commonpb/common_pb2.py
sliver/pb/commonpb/common_pb2.pyi
sliver/pb/rpcpb/__init__.py
sliver/pb/rpcpb/services_pb2.py
sliver/pb/rpcpb/services_pb2.pyi
sliver/pb/rpcpb/services_pb2_grpc.py
sliver/pb/rpcpb/services_pb2_grpc.pyi
sliver/pb/sliverpb/__init__.py
sliver/pb/sliverpb/sliver_pb2.py
sliver/pb/sliverpb/sliver_pb2.pyi
sliver_py-0.0.19.dist-info/METADATA
sliver_py-0.0.19.dist-info/WHEEL
sliver_py-0.0.19.dist-info/licenses/LICENSE
sliver_py-0.0.19.dist-info/RECORD
