Metadata-Version: 2.1
Name: sliver-py
Version: 0.0.19
Summary: Sliver gRPC client library.
Project-URL: Bug Tracker, https://github.com/moloch--/sliver-py/issues
Project-URL: Homepage, https://github.com/moloch--/sliver-py
Author-email: moloch <875022+moloch--@users.noreply.github.com>, daddycocoaman <daddycocoaman@gmail.com>
License-File: LICENSE
Classifier: Programming Language :: Python :: 3.7
Classifier: Programming Language :: Python :: 3.8
Classifier: Programming Language :: Python :: 3.9
Classifier: Programming Language :: Python :: 3.10
Requires-Python: >=3.7
Requires-Dist: grpcio-tools~=1.47
Requires-Dist: grpcio~=1.47
Requires-Dist: mypy-protobuf~=3.3.0
Requires-Dist: typing-extensions~=4.4.0; python_version < '3.8'
